_version.py
f4enix/__init__.py
f4enix/constants.py
f4enix/egroups.py
f4enix/material_library.py
f4enix/input/MCNPinput.py
f4enix/input/__init__.py
f4enix/input/ace.py
f4enix/input/auxiliary.py
f4enix/input/d1suned.py
f4enix/input/elite.py
f4enix/input/irradiation.py
f4enix/input/libmanager.py
f4enix/input/materials.py
f4enix/input/xsdirpyne.py
f4enix/input/ww_gvr/__init__.py
f4enix/input/ww_gvr/__main__.py
f4enix/input/ww_gvr/cli.py
f4enix/input/ww_gvr/geometry.py
f4enix/input/ww_gvr/meshgrids.py
f4enix/input/ww_gvr/models.py
f4enix/input/ww_gvr/ratios_calculation.py
f4enix/input/ww_gvr/utils.py
f4enix/input/ww_gvr/weight_window.py
f4enix/input/ww_gvr/ww_parser.py
f4enix/output/MCNPoutput.py
f4enix/output/__init__.py
f4enix/output/cuv_sampling_error.py
f4enix/output/decay_pathways.py
f4enix/output/eeout.py
f4enix/output/fispact_legacy_out.py
f4enix/output/mctal.py
f4enix/output/meshinfo.py
f4enix/output/plotter.py
f4enix/output/rssa.py
f4enix/output/meshtal/__init__.py
f4enix/output/meshtal/aux_meshtal_functions.py
f4enix/output/meshtal/fmesh.py
f4enix/output/meshtal/mesh_parser.py
f4enix/output/meshtal/meshtal.py
f4enix/resources/Isotopes.txt
f4enix/resources/__init__.py
f4enix/resources/activation_libs.xlsx
f4enix/resources/global_filterable.csv
f4enix/resources/half_lives_decay2020.json
f4enix/resources/xsdir.txt
f4enix-0.18.1.dist-info/licenses/LICENSE
f4enix-0.18.1.dist-info/METADATA
f4enix-0.18.1.dist-info/WHEEL
f4enix-0.18.1.dist-info/top_level.txt
f4enix-0.18.1.dist-info/RECORD
