Metadata-Version: 2.4
Name: f4enix
Version: 0.18.1
Summary: API for Monte Carlo input and output parsing
Author-email: F4E neutronics team <sc-radiationtransport@f4e.europa.eu>
Project-URL: Homepage, https://github.com/fusion4energy
Project-URL: Repository, https://github.com/Fusion4Energy/F4Enix
Project-URL: Documentation, https://f4enix.readthedocs.io/en/latest/
Classifier: Programming Language :: Python :: 3
Classifier: License :: OSI Approved :: European Union Public Licence 1.2 (EUPL 1.2)
Classifier: Operating System :: OS Independent
Requires-Python: >=3.10
License-File: LICENSE
Requires-Dist: numjuggler>=2.42.37
Requires-Dist: pyvista>=0.39.1
Requires-Dist: pandas
Requires-Dist: polars
Requires-Dist: numba
Requires-Dist: scipy
Requires-Dist: tqdm
Requires-Dist: python-docx
Requires-Dist: openpyxl
Requires-Dist: tables
Requires-Dist: endf
Requires-Dist: pypact>=1.3.8
Provides-Extra: tests
Requires-Dist: pytest; extra == "tests"
Requires-Dist: pytest-cov; extra == "tests"
Requires-Dist: nbformat; extra == "tests"
Requires-Dist: nbconvert; extra == "tests"
Requires-Dist: ipykernel; extra == "tests"
Dynamic: license-file
